{
  "movie_list": [
    {
      "id": 1,
      "title": "Squid Game Season 2",
      "episode": "7",
      "description": "Musim kedua dari serial televisi horor thriller survival distopia Korea Selatan Squid Game dibuat untuk televisi oleh penulis dan produser televisi Korea Hwang Dong-hyuk.<br><br>Diproduksi oleh Netflix, serial ini dirilis pada 26 Desember 2024.",
      "image": "/images/squid_game_s2.jpg",
      "genre": "Survival, Thriller, Horror, Series",
      "quality": "HD 1080p",
      "landing_page": true,
      "data": [
        {
          "episode": "1",
          "title": "Bread and Lottery",
          "iframe_link": "https://vidlink.pro/tv/93405/2/1"
        },
        {
          "episode": "2",
          "title": "Halloween Party",
          "iframe_link": "https://vidlink.pro/tv/93405/2/2"
        },
        {
          "episode": "3",
          "title": "001",
          "iframe_link": "https://vidlink.pro/tv/93405/2/3"
        },
        {
          "episode": "4",
          "title": "Six Legs",
          "iframe_link": "https://vidlink.pro/tv/93405/2/4"
        },
        {
          "episode": "5",
          "title": "One More Game",
          "iframe_link": "https://vidlink.pro/tv/93405/2/5"
        },
        {
          "episode": "6",
          "title": "O X",
          "iframe_link": "https://vidlink.pro/tv/93405/2/6"
        },
        {
          "episode": "7",
          "title": "Friend or Foe",
          "iframe_link": "https://vidlink.pro/tv/93405/2/7"
        }
      ]
    },
    {
      "id": 2,
      "title": "Dilan 1983 Wo Ai Ni",
      "episode": "1",
      "description": "Dilan 1983: Wo Ai Ni adalah film drama keluarga Indonesia tahun 2024 yang disutradarai oleh Fajar Bustomi dan ditulis oleh Pidi Baiq dan Alim Sudio.<br><br>Film tersebut merupakan prekuel dari film-film Dilan 1990, Dilan 1991, Milea: Suara dari Dilan dan Ancika: Dia yang Bersamaku 1995. Film ini dirilis pada 13 Juni 1983.[1]",
      "image": "/images/dilan_wo_ai_1983.jpg",
      "genre": "Romantis",
      "quality": "HD 720p",
      "landing_page": true,
      "data": [
        {
          "title": "Full Movie",
          "iframe_link": "https://play.save21.site/?url=https%3A%2F%2Fiplayerhls.com%2Fe%2Fp3xishmo9awd"
        }
      ]
    },
    {
      "id": 3,
      "title": "Janji Darah",
      "episode": "1",
      "description": "Janji Darah adalah sebuah film horor Indonesia tahun 2024 yang disutradarai oleh Sentot Sahid dan Andri Sofyansyah. Film tersebut menampilkan Natasha Wilona, Emir Mahira, Fergie Brittany, Djenar Maesa Ayu, Kiki Narendra, Abirama Putra, Yati Surachman, Emmie Lemu dan Shabrina Luna.",
      "image": "/images/janji_darah.jpeg",
      "quality": "HD 1080p",
      "genre": "Horror",
      "landing_page": false,
      "data": [
        {
          "title": "Full Movie",
          "iframe_link": "https://vidlink.pro/movie/1301273"
        }
      ]
    },
    {
      "id": 4,
      "genre": "Horror",
      "title": "Munkar",
      "episode": "1",
      "description": "Munkar adalah film horor Indonesia tahun 2024 yang disutradarai oleh Anggy Umbara. Film produksi MD Pictures serta Pichouse Films ini dibintangi oleh Adhisty Zara, Ratu Sofya, dan Saskia Chadwick. Munkar tayang perdana di bioskop Indonesia pada 7 Februari 2024.",
      "image": "/images/munkar.jpg",
      "quality": "HD 1080p",
      "landing_page": false,
      "data": [
        {
          "title": "Full Movie",
          "iframe_link": "https://vidlink.pro/movie/1163953"
        }
      ]
    },
    {
      "id": 5,
      "genre": "Drama",
      "title": "Jakarta vs Everybody",
      "episode": "1",
      "description": "Dom, seorang remaja yang sedang mencari jati diri, mencoba segala cara untuk mencapai mimpinya sebagai seorang aktor di Jakarta.<br>Setelah serangkaian audisi yang gagal, Dom bertemu Radit dan Pinkan, seorang pasangan muda yang memberikannya pekerjaan.<br>Menggunakan keterampilan aktingnya untuk berperan sebagai karakter yang berbeda, Dom terjemus dalam dunia hitam.",
      "image": "/images/jakarta-vs-everybody.jpg",
      "quality": "HD 1080p",
      "landing_page": false,
      "data": [
        {
          "title": "Full Movie",
          "iframe_link": "https://vidsrc.xyz/embed/movie/551478"
        }
      ]
    },
    {
      "id": 6,
      "genre": "Horror, Survival",
      "title": "Dosen Ghaib",
      "episode": "1",
      "description": "Film ini menceritakan tentang empat mahasiswa, Amelia, Emir, Maya, dan Fattah, yang harus mengikuti kelas semester pendek setelah gagal dalam mata kuliah Pak Bakti.<br>Pak Bakti adalah dosen yang dikenal galak, misterius, dan memiliki kemampuan gaib.",
      "image": "/images/GSwLH28a8AA_GGt.jpg_large",
      "quality": "HD 1080p",
      "landing_page": true,
      "data": [
        {
          "title": "Full Movie",
          "iframe_link": "https://vidsrc.xyz/embed/movie/1264247"
        }
      ]
    },
    {
      "id": 7,
      "genre": "Horror, Survival, Kisah Nyata",
      "title": "Rumah Dinas Bapak",
      "episode": "1",
      "description": "Film Rumah Dinas Bapak merupakan film yang diangkat dari kisah nyata masa kecil yang dialami oleh Dodit Mulyanto dan keluarganya.<br>Sinopsis film ini mengikuti kisah keluarga Dodit yang harus pindah ke rumah dinas tempat ayahnya bekerja sebagai polisi di hutan jati.",
      "image": "/images/oofvIRqMT4aGqa3IuMjCwp4cj6J.jpg",
      "quality": "HD 1080p",
      "landing_page": false,
      "data": [
        {
          "title": "Full Movie",
          "iframe_link": "https://vidsrc.xyz/embed/movie/1281437"
        }
      ]
    },
    {
      "id": 8,
      "genre": "Horror, Survival, Kisah Nyata",
      "title": "Badarawuhi Di Desa Penari",
      "episode": "1",
      "description": "Badarawuhi di Desa Penari adalah film yang menceritakan tentang Mila, seorang anak yang pergi ke Desa Penari untuk mencari obat bagi ibunya yang sakit keras.<br>Di sana, Mila bertemu dengan Badarawuhi, sosok iblis ular yang ingin menjadikan Mila sebagai penari desa.",
      "image": "/images/b7386d86be102556ea1faaf905aae341.jpg",
      "quality": "HD 1080p",
      "landing_page": false,
      "data": [
        {
          "title": "Full Movie",
          "iframe_link": "https://vidsrc.xyz/embed/movie/1176166"
        }
      ]
    },
    {
      "id": 9,
      "genre": "Fiksi, Survival, Drama, Petualangan",
      "title": "Interstellar (2014)",
      "episode": "1",
      "description": "Sebuah tim penjelajah antar galaksi harus melewati lubang cacing dan terjebak di dimensi waktu ruang angkasa dalam upaya untuk menjamin kelangsungan hidup umat manusia di planet bumi.",
      "image": "/images/wp12464977.jpg",
      "quality": "HD 1080p",
      "landing_page": false,
      "data": [
        {
          "title": "Full Movie",
          "iframe_link": "https://embed.su/embed/movie/157336"
        }
      ]
    },
    {
      "id": 10,
      "genre": "Komedi, Drama",
      "title": "Guru Guru Gokil",
      "episode": "1",
      "description": "Guru-Guru Gokil bercerita tentang Taat (Gading Marten) yang berambisi untuk sukses, tapi lebih sering menemui kegagalan dalam karier. Baginya, kesuksesan berarti memiliki uang banyak.<br>Hingga suatu saat, keadaan mengharuskan Taat untuk bekerja menjadi guru di sebuah sekolah.",
      "image": "/images/1e83c4ba133007a04922911403ec4895.jpg",
      "quality": "HD 1080p",
      "landing_page": false,
      "data": [
        {
          "title": "Full Movie",
          "iframe_link": "https://vidlink.pro/movie/655832"
        }
      ]
    },
    {
      "id": 11,
      "genre": "Komedi, Drama, Romantis",
      "title": "Lara Ati",
      "episode": "1",
      "description": "Joko menghadapi kenyataan bahwa ia tidak menyukai pekerjaannya dan orangtuanya tidak mendukung mimpinya menjadi seorang pekerja desain.<br>Ditambah lagi, Joko ditinggal tunangan oleh pacarnya, Farah. Hidup Joko berantakan.",
      "image": "/images/1.jpg",
      "quality": "HD 720p",
      "landing_page": false,
      "data": [
        {
          "title": "Full Movie",
          "iframe_link": "https://vidlink.pro/movie/802706"
        }
      ]
    }
  ]
}
